one/__init__.py
one/_version.py
one/one.py
one_dot_py-1.0.2.dist-info/METADATA
one_dot_py-1.0.2.dist-info/WHEEL
one_dot_py-1.0.2.dist-info/licenses/LICENSE
one_dot_py-1.0.2.dist-info/RECORD
