Metadata-Version: 2.4
Name: one-dot-py
Version: 1.0.2
Summary: Add your description here
Project-URL: Documentation, https://xkcd.com/730/
Project-URL: Source (GitHub), https://github.com/anamoyee/one
Author: anamoyee
License: GPL-3.0
License-File: LICENSE
Classifier: Development Status :: 3 - Alpha
Classifier: Operating System :: MacOS
Classifier: Operating System :: Microsoft :: MS-DOS
Classifier: Operating System :: Microsoft :: Windows
Classifier: Operating System :: POSIX
Classifier: Operating System :: POSIX :: Linux
Classifier: Programming Language :: Python :: 3
Classifier: Programming Language :: Python :: 3 :: Only
Classifier: Programming Language :: Python :: 3.9
Classifier: Programming Language :: Python :: 3.10
Classifier: Programming Language :: Python :: 3.11
Classifier: Programming Language :: Python :: 3.12
Classifier: Programming Language :: Python :: 3.13
Classifier: Programming Language :: Python :: 3.14
Classifier: Topic :: Utilities
Requires-Python: >=3.9
Requires-Dist: inflect<8.0.0,>=7.5.0
